deepctl_cmd_debug_audio/__init__.py
deepctl_cmd_debug_audio/command.py
deepctl_cmd_debug_audio/models.py
deepctl_cmd_debug_audio-0.1.10.dist-info/METADATA
deepctl_cmd_debug_audio-0.1.10.dist-info/WHEEL
deepctl_cmd_debug_audio-0.1.10.dist-info/entry_points.txt
deepctl_cmd_debug_audio-0.1.10.dist-info/top_level.txt
deepctl_cmd_debug_audio-0.1.10.dist-info/RECORD
